<?xml version="1.0" encoding="utf-8" ?>
<dwsync>
<file name="styleDesktop.css" server="ftp.davidcthames.com/mathio/" local="130966472891547215" remote="130966400400000000" Dst="1" />
<file name="blur.svg" server="ftp.davidcthames.com/mathio/" local="130476193940000000" remote="130828349400000000" Dst="2" />
<file name="demo.css" server="ftp.davidcthames.com/mathio/" local="130463989560000000" remote="130828349400000000" Dst="2" />
<file name="DesktopHome.css" server="ftp.davidcthames.com/mathio/" local="130858731873680703" remote="130881092400000000" Dst="2" />
<file name="DesktopHome2.css" server="ftp.davidcthames.com/mathio/" local="130716323960000000" remote="130828349400000000" Dst="2" />
<file name="gettingStarted.css" server="ftp.davidcthames.com/mathio/" local="130796554900397740" remote="130828349400000000" Dst="2" />
<file name="normalize.css" server="ftp.davidcthames.com/mathio/" local="130463985140000000" remote="130828349400000000" Dst="2" />
<file name="style-old.css" server="ftp.davidcthames.com/mathio/" local="130716323970000000" remote="130828349400000000" Dst="2" />
<file name="simple.css" server="ftp.davidcthames.com/mathio/" local="130571174200000000" remote="130828349400000000" Dst="2" />
<file name="styleMobile.css" server="ftp.davidcthames.com/mathio/" local="130716323970000000" remote="130828349400000000" Dst="2" />
<file name="template.css" server="ftp.davidcthames.com/mathio/" local="130463985150000000" remote="130828349400000000" Dst="2" />
<file name="blur.svg" server="ftp.davidcthames.com/mathio/transitions/" local="130476193940000000" remote="130828419000000000" Dst="2" />
<file name="demo.css" server="ftp.davidcthames.com/mathio/transitions/" local="130463989560000000" remote="130828419000000000" Dst="2" />
<file name="DesktopHome.css" server="ftp.davidcthames.com/mathio/transitions/" local="130828498663167033" remote="130828419000000000" Dst="2" />
<file name="DesktopHome2.css" server="ftp.davidcthames.com/mathio/transitions/" local="130716323960000000" remote="130828419000000000" Dst="2" />
<file name="gettingStarted.css" server="ftp.davidcthames.com/mathio/transitions/" local="130796554900397740" remote="130828419000000000" Dst="2" />
<file name="normalize.css" server="ftp.davidcthames.com/mathio/transitions/" local="130463985140000000" remote="130828419000000000" Dst="2" />
<file name="simple.css" server="ftp.davidcthames.com/mathio/transitions/" local="130571174200000000" remote="130828419000000000" Dst="2" />
<file name="style-old.css" server="ftp.davidcthames.com/mathio/transitions/" local="130716323970000000" remote="130828419000000000" Dst="2" />
<file name="styleDesktop.css" server="ftp.davidcthames.com/mathio/transitions/" local="130822278669880851" remote="130828419000000000" Dst="2" />
<file name="template.css" server="ftp.davidcthames.com/mathio/transitions/" local="130463985150000000" remote="130828419000000000" Dst="2" />
<file name="styleMobile.css" server="ftp.davidcthames.com/mathio/transitions/" local="130716323970000000" remote="130828419000000000" Dst="2" />
<file name="lessons.css" server="ftp.davidcthames.com/mathio/" local="130832998865778119" remote="130832890800000000" Dst="2" />
<file name="about.css" server="ftp.davidcthames.com/mathio/" local="130895037530000000" remote="130957092600000000" Dst="1" />
</dwsync>