<?xml version="1.0" encoding="utf-8" ?>
<dwsync>
<file name="accountSummary.php" server="ftp.davidcthames.com/mathio/" local="130858707775390957" remote="130877855400000000" Dst="2" />
<file name="accountSignin.html" server="ftp.davidcthames.com/mathio/" local="130821590749168944" remote="130828351200000000" Dst="2" />
<file name="accountSummary.html" server="ftp.davidcthames.com/mathio/" local="130601156110000000" remote="130828351200000000" Dst="2" />
<file name="dashboard.php" server="ftp.davidcthames.com/mathio/" local="130825910979401829" remote="130828351200000000" Dst="2" />
<file name="logout.php" server="ftp.davidcthames.com/mathio/" local="130601156110000000" remote="130828351200000000" Dst="2" />
<file name="status.php" server="ftp.davidcthames.com/mathio/" local="130716324040000000" remote="130828351200000000" Dst="2" />
<file name="passTest.php" server="ftp.davidcthames.com/mathio/" local="130601156110000000" remote="130828351200000000" Dst="2" />
<file name="accountSignin.html" server="ftp.davidcthames.com/mathio/transitions/" local="130821590749168944" remote="130828420800000000" Dst="2" />
<file name="accountSummary.html" server="ftp.davidcthames.com/mathio/transitions/" local="130601156110000000" remote="130828420800000000" Dst="2" />
<file name="accountSummary.php" server="ftp.davidcthames.com/mathio/transitions/" local="130822276008548447" remote="130828420800000000" Dst="2" />
<file name="logout.php" server="ftp.davidcthames.com/mathio/transitions/" local="130601156110000000" remote="130828420800000000" Dst="2" />
<file name="dashboard.php" server="ftp.davidcthames.com/mathio/transitions/" local="130828522801023334" remote="130828420800000000" Dst="2" />
<file name="passTest.php" server="ftp.davidcthames.com/mathio/transitions/" local="130601156110000000" remote="130828420800000000" Dst="2" />
<file name="status.php" server="ftp.davidcthames.com/mathio/transitions/" local="130716324040000000" remote="130828420800000000" Dst="2" />
</dwsync>